bigmultipipe/__init__.py
bigmultipipe/argparse_handler.py
bigmultipipe/bigmultipipe.py
bigmultipipe/bigmultipipe_example.py
bigmultipipe-0.2.0.dist-info/LICENSE
bigmultipipe-0.2.0.dist-info/METADATA
bigmultipipe-0.2.0.dist-info/WHEEL
bigmultipipe-0.2.0.dist-info/top_level.txt
bigmultipipe-0.2.0.dist-info/RECORD
