Metadata-Version: 2.1
Name: bigmultipipe
Version: 0.2.0
Summary: Process big data efficiently
Home-page: http://bigmultipipe.readthedocs.io/
Author: Jeffrey P. Morgenthaler
License: MIT
License-File: LICENSE
Requires-Dist: psutil
